{
  "Name": "Red Coin System",
  "Author": "Evanbowl",
  "Description": "PTD: Red Coin System",
  "InstallDependencies": ["Syati_ObjectFactories", "Syati_Init", "CustomCoinSpawns"],
  "CompilerFlags" : [
    "-DREDCOINSYSTEM"
  ],
  "ModuleData" : [
    {
      "NameObjFactory": [
        {
          "Name" : "RedCoin",
          "Function" : "createExtActor<RedCoin>",
          "Include" : "RedCoin.h"
        },
        {
          "Name" : "RedCoinController",
          "Function" : "createExtActor<RedCoinController>",
          "Include" : "RedCoinController.h"
        },
        {
          "Name" : "RedCoinSwitch",
          "Function" : "createExtActor<RedCoinSwitch>",
          "Include" : "RedCoinSwitch.h"
        }
      ]
    }
  ]
}